json_rd/__init__.py
json_rd/lexer.py
json_rd/parser_.py
json_rd/syntax_error.py
json_rd/token_.py
json_rd-1.0.dist-info/LICENSE
json_rd-1.0.dist-info/METADATA
json_rd-1.0.dist-info/WHEEL
json_rd-1.0.dist-info/top_level.txt
json_rd-1.0.dist-info/RECORD
